MANIFEST.in
README.txt
plonetheme.laboral-configure.zcml
setup.cfg
setup.py
docs/HISTORY.txt
docs/INSTALL.txt
docs/LICENSE.GPL
docs/LICENSE.txt
plonetheme/__init__.py
plonetheme.laboral.egg-info/PKG-INFO
plonetheme.laboral.egg-info/SOURCES.txt
plonetheme.laboral.egg-info/dependency_links.txt
plonetheme.laboral.egg-info/entry_points.txt
plonetheme.laboral.egg-info/namespace_packages.txt
plonetheme.laboral.egg-info/not-zip-safe
plonetheme.laboral.egg-info/paster_plugins.txt
plonetheme.laboral.egg-info/requires.txt
plonetheme.laboral.egg-info/top_level.txt
plonetheme/laboral/__init__.py
plonetheme/laboral/configure.zcml
plonetheme/laboral/profiles.zcml
plonetheme/laboral/setuphandlers.py
plonetheme/laboral/skins.zcml
plonetheme/laboral/tests.py
plonetheme/laboral/version.txt
plonetheme/laboral/Extensions/Install.py
plonetheme/laboral/browser/__init__.py
plonetheme/laboral/browser/collection.pt
plonetheme/laboral/browser/configure.zcml
plonetheme/laboral/browser/file_view.pt
plonetheme/laboral/browser/file_view.py
plonetheme/laboral/browser/footer.pt
plonetheme/laboral/browser/head.pt
plonetheme/laboral/browser/interfaces.py
plonetheme/laboral/browser/laboral_file_view.pt
plonetheme/laboral/browser/laboral_file_view.py
plonetheme/laboral/browser/laboral_folder_view.pt
plonetheme/laboral/browser/laboral_folder_view.py
plonetheme/laboral/browser/laboral_slider_view.pt
plonetheme/laboral/browser/laboral_slider_view.py
plonetheme/laboral/browser/leadimage-body.pt
plonetheme/laboral/browser/logo.pt
plonetheme/laboral/browser/searchview.py
plonetheme/laboral/browser/sections.pt
plonetheme/laboral/browser/slider.pt
plonetheme/laboral/browser/viewlet.pt
plonetheme/laboral/browser/viewlets.py
plonetheme/laboral/browser/visualClear.pt
plonetheme/laboral/browser/images/README.txt
plonetheme/laboral/browser/images/background.jpg
plonetheme/laboral/browser/images/eventDatePast.jpg
plonetheme/laboral/browser/images/facebook.png
plonetheme/laboral/browser/images/facebook_hover.png
plonetheme/laboral/browser/images/loader_animated.gif
plonetheme/laboral/browser/images/searchglass.png
plonetheme/laboral/browser/images/share.png
plonetheme/laboral/browser/images/share_hover.png
plonetheme/laboral/browser/images/stumbleupon.png
plonetheme/laboral/browser/images/stumbleupon_hover.png
plonetheme/laboral/browser/images/twitter.png
