Metadata-Version: 1.0
Name: plonetheme.laboral
Version: 3.10
Summary: An installable theme for Plone 4
Home-page: http://svn.plone.org/svn/collective/plonetheme.laboral
Author: David Jonas
Author-email: davidjonasdesign@gmail.com
License: GPL
Keywords: web zope plone theme
Platform: UNKNOWN
Classifier: Framework :: Plone
Classifier: Programming Language :: Python
